namely/__init__.py
namely/_config.py
namely/client.py
namely/exceptions.py
namely/resources/__init__.py
namely/resources/helpers.py
namely/resources/profiles.py
namely-0.0.3.dist-info/LICENSE
namely-0.0.3.dist-info/WHEEL
namely-0.0.3.dist-info/METADATA
namely-0.0.3.dist-info/RECORD
