Metadata-Version: 2.1
Name: namely
Version: 0.0.3
Summary: Namely Python Client
Home-page: https://github.com/VadymKhodak/namely
Author: VadymKhodak
Author-email: vaddimart@gmail.com
Requires-Python: >=3.7
Classifier: License :: OSI Approved :: MIT License
Requires-Dist: requests==2.25.1
Requires-Dist: retrying==1.3.3
Project-URL: Documentation, https://namely.readthedocs.io/en/latest/
